{"pages": [{"title": "Front App API Getting Started", "path": "getting-started", "anchors": [{"id": "", "keywords": ["getting", "started", "conversation", "useragent", "stream", "session", "javascript", "angular", "react", "vue", "android", "ios", "apple"]}]}, {"title": "Architecture", "path": "architecture", "anchors": [{"id": "", "keywords": ["apirtc", "application", "backend", "client", "paas", "platform", "portal", "hook", "webhooks", "restful", "sfu", "signaling", "stun", "turn", "storage", "users", "management"]}]}, {"title": "Logical Concepts", "path": "logical-concepts", "anchors": [{"id": "", "keywords": ["account", "enterprise", "apiKey", "users", "conversation", "billing", "price", "usage"]}]}, {"title": "Front App API Developer Guide", "path": "dev-guide", "anchors": [{"id": "apikey", "keywords": ["apikey"]}, {"id": "user-agent", "keywords": ["user", "agent"]}, {"id": "session", "keywords": ["session"]}, {"id": "authentication", "keywords": ["authentication"]}, {"id": "presence", "keywords": ["presence"]}, {"id": "conversation", "keywords": ["conversation"]}, {"id": "moderation", "keywords": ["moderation"]}, {"id": "local-streams", "keywords": ["local", "streams"]}, {"id": "camera", "keywords": ["camera"]}, {"id": "screen-sharing", "keywords": ["screen", "sharing"]}, {"id": "publish-unpublish", "keywords": ["publish", "unpublish"]}, {"id": "remote-streams", "keywords": ["remote", "streams"]}, {"id": "stream-display", "keywords": ["stream", "display"]}, {"id": "stream-constraints", "keywords": ["stream", "constraints", "constraint", "capabilities", "capability", "setting", "property", "applyconstraint", "resolution", "brightness", "contrast", "frameRate", "saturation", "torch", "zoom", "remote control", "device"]}, {"id": "qos-statistics", "keywords": ["qos", "statistics"]}, {"id": "speaker-detection", "keywords": ["speaker", "detection"]}, {"id": "mute", "keywords": ["mute", "muting"]}, {"id": "whiteboard", "keywords": ["whiteboard", "whiteboard", "board", "screen"]}, {"id": "recording", "keywords": ["recording", "video", "composite"]}, {"id": "chat-messages", "keywords": ["chat", "messages"]}, {"id": "background-subtraction", "keywords": ["background", "subtraction", "blur"]}, {"id": "good-practices", "keywords": ["good", "practices"]}]}, {"title": "React UI Library Developer Guide", "path": "react-ui-dev-guide", "anchors": [{"id": "", "keywords": ["react", "ui", "gui", "graphical", "components"]}, {"id": "useapirtc", "keywords": ["useapirtc"]}, {"id": "login", "keywords": ["login"]}, {"id": "agenda", "keywords": ["agenda"]}, {"id": "chat", "keywords": ["chat"]}, {"id": "whiteboard", "keywords": ["whiteboard"]}]}, {"title": "Platform Developer Guide", "path": "platform-dev-guide", "anchors": [{"id": "platform", "keywords": ["platform"]}, {"id": "rest-api", "keywords": ["rest", "api"]}, {"id": "authentication", "keywords": ["authentication"]}, {"id": "provisioning", "keywords": ["provisioning"]}, {"id": "medias", "keywords": ["medias"]}, {"id": "webhooks", "keywords": ["webhooks"]}]}, {"title": "Demo", "path": "demo", "anchors": [{"id": "", "keywords": ["demo", "angular", "javascript", "tutorial", "samples", "examples"]}]}, {"title": "Samples", "path": "examples", "anchors": [{"id": "", "keywords": ["samples", "javascript", "tutorial", "examples"]}]}]}
